TouchPortalAPI/TpToPy.py
TouchPortalAPI/__init__.py
TouchPortalAPI/client.py
TouchPortalAPI/logger.py
TouchPortalAPI/sdk_spec.py
TouchPortalAPI/sdk_tools.py
TouchPortalAPI/tools.py
TouchPortalAPI/tppbuild.py
TouchPortalAPI/tppdoc.py
touchportal_api-1.7.10.dist-info/LICENCE.txt
touchportal_api-1.7.10.dist-info/METADATA
touchportal_api-1.7.10.dist-info/WHEEL
touchportal_api-1.7.10.dist-info/entry_points.txt
touchportal_api-1.7.10.dist-info/top_level.txt
touchportal_api-1.7.10.dist-info/RECORD
