Metadata-Version: 2.1
Name: touchportal-api
Version: 1.7.10
Summary: Touch Portal API and SDK for Python
Home-page: https://github.com/KillerBOSS2019/TouchPortal-API/
Author: Damien
Author-email: DamienWeiFen@gmail.com
License: GPLv3+
Project-URL: Documentation, https://KillerBOSS2019.github.io/TouchPortal-API/
Project-URL: Source, https://github.com/KillerBOSS2019/TouchPortal-API/
Project-URL: Issues, https://github.com/KillerBOSS2019/TouchPortal-API/issues
Keywords: TouchPortal,Touch Portal,API,Plugin,SDK
Classifier: Development Status :: 5 - Production/Stable
Classifier: Intended Audience :: Developers
Classifier: Operating System :: Microsoft :: Windows :: Windows 10
Classifier: Operating System :: MacOS
Classifier: License :: OSI Approved :: GNU General Public License v3 or later (GPLv3+)
Classifier: Programming Language :: Python :: 3
Classifier: Programming Language :: Python :: 3.8
Classifier: Programming Language :: Python :: 3.9
Classifier: Programming Language :: Python :: 3.10
Requires-Python: >=3.8
License-File: LICENCE.txt
Requires-Dist: pyee
Requires-Dist: requests
Provides-Extra: dev
Requires-Dist: pdoc ; extra == 'dev'
Provides-Extra: optional
Requires-Dist: Pyinstaller ; extra == 'optional'
